{"root":[{"assemblyName":"UnityEngine.Purchasing.Codeless","nameSpace":"UnityEngine.Purchasing","className":"CodelessIAPStoreListener","methodName":"InitializeCodelessPurchasingOnLoad","loadTypes":0,"isUnityClass":true},{"assemblyName":"BehaviorDesigner.Runtime","nameSpace":"BehaviorDesigner.Runtime","className":"Behavior","methodName":"DomainReset","loadTypes":4,"isUnityClass":false},{"assemblyName":"BehaviorDesigner.Runtime","nameSpace":"BehaviorDesigner.Runtime","className":"BehaviorManager","methodName":"DomainReset","loadTypes":4,"isUnityClass":false},{"assemblyName":"BehaviorDesigner.Runtime","nameSpace":"BehaviorDesigner.Runtime","className":"GlobalVariables","methodName":"DomainReset","loadTypes":4,"isUnityClass":false}]}
